{
  "resolvedId": "/Users/ilaolovannikov/WebstormProjects/cognitive-lab/src/entities/Test/ui/TestContainer/index.tsx",
  "transforms": [
    {
      "name": "vite:load-fallback",
      "result": "import type { PropsWithChildren } from 'react';\nimport { Box, Container } from '@mantine/core';\n\nimport s from './TestContainer.module.css';\n\nexport const TestContainer = ({ children }: PropsWithChildren) => (\n    <Box component='section'>\n        <Container className={s.container}>{children}</Container>\n    </Box>\n);\n",
      "start": 1750239308406,
      "end": 1750239308419,
      "sourcemaps": null
    },
    {
      "name": "vite:react-swc",
      "result": "import { jsx as _jsx } from \"react/jsx-runtime\";\nimport { Box, Container } from '@mantine/core';\nimport s from './TestContainer.module.css';\nexport const TestContainer = ({ children })=>/*#__PURE__*/ _jsx(Box, {\n        component: \"section\",\n        children: /*#__PURE__*/ _jsx(Container, {\n            className: s.container,\n            children: children\n        })\n    });\n",
      "start": 1750239308419,
      "end": 1750239308423,
      "order": "pre",
      "sourcemaps": "{\"version\":3,\"sources\":[\"/Users/ilaolovannikov/WebstormProjects/cognitive-lab/src/entities/Test/ui/TestContainer/index.tsx\"],\"sourcesContent\":[\"import type { PropsWithChildren } from 'react';\\nimport { Box, Container } from '@mantine/core';\\n\\nimport s from './TestContainer.module.css';\\n\\nexport const TestContainer = ({ children }: PropsWithChildren) => (\\n    <Box component='section'>\\n        <Container className={s.container}>{children}</Container>\\n    </Box>\\n);\\n\"],\"names\":[\"Box\",\"Container\",\"s\",\"TestContainer\",\"children\",\"component\",\"className\",\"container\"],\"mappings\":\";AACA,SAASA,GAAG,EAAEC,SAAS,QAAQ,gBAAgB;AAE/C,OAAOC,OAAO,6BAA6B;AAE3C,OAAO,MAAMC,gBAAgB,CAAC,EAAEC,QAAQ,EAAqB,iBACzD,KAACJ;QAAIK,WAAU;kBACX,cAAA,KAACJ;YAAUK,WAAWJ,EAAEK,SAAS;sBAAGH;;OAE1C\"}"
    },
    {
      "name": "vite:esbuild",
      "result": "import { jsx as _jsx } from \"react/jsx-runtime\";\nimport { Box, Container } from \"@mantine/core\";\nimport s from \"./TestContainer.module.css\";\nexport const TestContainer = ({ children }) => /* @__PURE__ */ _jsx(Box, {\n  component: \"section\",\n  children: /* @__PURE__ */ _jsx(Container, {\n    className: s.container,\n    children\n  })\n});\n",
      "start": 1750239308423,
      "end": 1750239308605,
      "order": "normal",
      "sourcemaps": {
        "version": 3,
        "sources": [
          "/Users/ilaolovannikov/WebstormProjects/cognitive-lab/src/entities/Test/ui/TestContainer/index.tsx"
        ],
        "sourcesContent": [
          "import { jsx as _jsx } from \"react/jsx-runtime\";\nimport { Box, Container } from '@mantine/core';\nimport s from './TestContainer.module.css';\nexport const TestContainer = ({ children })=>/*#__PURE__*/ _jsx(Box, {\n        component: \"section\",\n        children: /*#__PURE__*/ _jsx(Container, {\n            className: s.container,\n            children: children\n        })\n    });\n"
        ],
        "mappings": "AAAA,SAAS,OAAO,YAAY;AAC5B,SAAS,KAAK,iBAAiB;AAC/B,OAAO,OAAO;AACP,aAAM,gBAAgB,CAAC,EAAE,SAAS,MAAkB,qBAAK,KAAK;AAAA,EAC7D,WAAW;AAAA,EACX,UAAwB,qBAAK,WAAW;AAAA,IACpC,WAAW,EAAE;AAAA,IACb;AAAA,EACJ,CAAC;AACL,CAAC;",
        "names": []
      }
    },
    {
      "name": "vite:worker",
      "start": 1750239308605,
      "end": 1750239308605,
      "order": "normal-normal"
    },
    {
      "name": "vike:fileEnv",
      "start": 1750239308605,
      "end": 1750239308605,
      "order": "normal"
    },
    {
      "name": "vite:build-html",
      "start": 1750239308605,
      "end": 1750239308605,
      "order": "normal-normal"
    },
    {
      "name": "vite:dynamic-import-vars",
      "start": 1750239308605,
      "end": 1750239308605,
      "order": "normal-normal"
    },
    {
      "name": "vite:import-glob",
      "start": 1750239308605,
      "end": 1750239308605,
      "order": "normal-normal"
    },
    {
      "name": "vike:extractAssets:remove-javaScript",
      "start": 1750239308605,
      "end": 1750239308605,
      "order": "post"
    },
    {
      "name": "vike:extractExportNames",
      "start": 1750239308605,
      "end": 1750239308605,
      "order": "post"
    },
    {
      "name": "vike:envVars",
      "start": 1750239308605,
      "end": 1750239308605,
      "order": "post"
    },
    {
      "name": "vite:build-import-analysis",
      "start": 1750239308605,
      "end": 1750239308605,
      "order": "normal-normal"
    },
    {
      "name": "vite:reporter",
      "start": 1750239308605,
      "end": 1750239308605,
      "order": "normal"
    },
    {
      "name": "vite:define",
      "start": 1750239308605,
      "end": 1750239308605,
      "order": "normal-normal"
    },
    {
      "name": "vike:pluginModuleBanner",
      "result": "/*! src/entities/Test/ui/TestContainer/index.tsx [vike:pluginModuleBanner] */\nimport { jsx as _jsx } from \"react/jsx-runtime\";\nimport { Box, Container } from \"@mantine/core\";\nimport s from \"./TestContainer.module.css\";\nexport const TestContainer = ({ children }) => /* @__PURE__ */ _jsx(Box, {\n  component: \"section\",\n  children: /* @__PURE__ */ _jsx(Container, {\n    className: s.container,\n    children\n  })\n});\n",
      "start": 1750239308605,
      "end": 1750239308605,
      "order": "post-post",
      "sourcemaps": {
        "version": 3,
        "sources": ["src/entities/Test/ui/TestContainer/index.tsx"],
        "names": [],
        "mappings": ";AAAA,CAAC,CAAC,CAAC,CAAC,CAAC,CAAC,CAAC,CAAC,CAAC,CAAC,CAAC,CAAC,CAAC,CAAC,CAAC,CAAC,CAAC,CAAC,CAAC,CAAC,CAAC,CAAC,CAAC,CAAC,CAAC,CAAC,CAAC,CAAC,CAAC,CAAC,CAAC,CAAC,CAAC,CAAC,CAAC,CAAC,CAAC,CAAC,CAAC,CAAC,CAAC,CAAC,CAAC,CAAC,CAAC,CAAC,CAAC;AAC/C,CAAC,CAAC,CAAC,CAAC,CAAC,CAAC,CAAC,CAAC,CAAC,CAAC,CAAC,CAAC,CAAC,CAAC,CAAC,CAAC,CAAC,CAAC,CAAC,CAAC,CAAC,CAAC,CAAC,CAAC,CAAC,CAAC,CAAC,CAAC,CAAC,CAAC,CAAC,CAAC,CAAC,CAAC,CAAC,CAAC,CAAC,CAAC,CAAC,CAAC,CAAC,CAAC,CAAC,CAAC,CAAC,CAAC;AAC9C,CAAC,CAAC,CAAC,CAAC,CAAC,CAAC,CAAC,CAAC,CAAC,CAAC,CAAC,CAAC,CAAC,CAAC,CAAC,CAAC,CAAC,CAAC,CAAC,CAAC,CAAC,CAAC,CAAC,CAAC,CAAC,CAAC,CAAC,CAAC,CAAC,CAAC,CAAC,CAAC,CAAC,CAAC,CAAC,CAAC,CAAC,CAAC,CAAC,CAAC,CAAC,CAAC;AAC1C,CAAC,CAAC,CAAC,CAAC,CAAC,CAAC,CAAC,CAAC,CAAC,CAAC,CAAC,CAAC,CAAC,CAAC,CAAC,CAAC,CAAC,CAAC,CAAC,CAAC,CAAC,CAAC,CAAC,CAAC,CAAC,CAAC,CAAC,CAAC,CAAC,CAAC,CAAC,CAAC,CAAC,CAAC,CAAC,CAAC,CAAC,CAAC,CAAC,CAAC,CAAC,CAAC,CAAC,CAAC,CAAC,CAAC,CAAC,CAAC,CAAC,CAAC,CAAC,CAAC,CAAC,CAAC,CAAC,CAAC,CAAC,CAAC,CAAC,CAAC,CAAC,CAAC,CAAC,CAAC,CAAC,CAAC,CAAC,CAAC,CAAC,CAAC,CAAC,CAAC,CAAC;AACzE,CAAC,CAAC,CAAC,CAAC,CAAC,CAAC,CAAC,CAAC,CAAC,CAAC,CAAC,CAAC,CAAC,CAAC,CAAC,CAAC,CAAC,CAAC,CAAC,CAAC,CAAC,CAAC;AACtB,CAAC,CAAC,CAAC,CAAC,CAAC,CAAC,CAAC,CAAC,CAAC,CAAC,CAAC,CAAC,CAAC,CAAC,CAAC,CAAC,CAAC,CAAC,CAAC,CAAC,CAAC,CAAC,CAAC,CAAC,CAAC,CAAC,CAAC,CAAC,CAAC,CAAC,CAAC,CAAC,CAAC,CAAC,CAAC,CAAC,CAAC,CAAC,CAAC,CAAC,CAAC,CAAC,CAAC,CAAC;AAC5C,CAAC,CAAC,CAAC,CAAC,CAAC,CAAC,CAAC,CAAC,CAAC,CAAC,CAAC,CAAC,CAAC,CAAC,CAAC,CAAC,CAAC,CAAC,CAAC,CAAC,CAAC,CAAC,CAAC,CAAC,CAAC,CAAC;AAC1B,CAAC,CAAC,CAAC,CAAC,CAAC,CAAC,CAAC,CAAC,CAAC,CAAC,CAAC;AACX,CAAC,CAAC,CAAC;AACH,CAAC,CAAC;"
      }
    }
  ]
}
