{
  "resolvedId": "/Users/ilaolovannikov/WebstormProjects/cognitive-lab/src/pages/IndexPage/ui/About/About.module.css",
  "transforms": [
    {
      "name": "vite:load-fallback",
      "result": ".grid {\n  @mixin larger-than 992px {\n    display: grid;\n    place-items: center;\n    grid-auto-rows: 0fr;\n    grid-template-areas:\n      \"l t2\"\n      \"l t2\";\n  }\n}\n\np.description {\n  grid-area: t;\n  font-weight: 500;\n  font-size: 19px;\n  line-height: 24px;\n\n  &:not(:last-of-type) {\n    margin-bottom: 16px;\n  }\n\n  &:last-of-type {\n    grid-area: t2;\n    margin-bottom: 40px;\n  }\n\n  @mixin larger-than 768px {\n    font-size: 32px;\n    line-height: 50px;\n  }\n}\n\npicture.image,\npicture.image img {\n  grid-area: l;\n  margin: 0 auto;\n  width: 210px;\n  height: 223px;\n\n  @mixin larger-than 992px {\n    margin-right: 132px;\n    width: 366px !important;\n    height: 388px !important;\n  }\n}\n",
      "start": 1746125696645,
      "end": 1746125696678,
      "sourcemaps": null
    },
    {
      "name": "vite:react-babel",
      "start": 1746125696678,
      "end": 1746125696678,
      "order": "pre"
    },
    {
      "name": "vite:esbuild",
      "start": 1746125696680,
      "end": 1746125696680,
      "order": "normal"
    },
    {
      "name": "vite:worker",
      "start": 1746125696680,
      "end": 1746125696680,
      "order": "normal-normal"
    },
    {
      "name": "vike:fileEnv",
      "start": 1746125696680,
      "end": 1746125696680,
      "order": "normal"
    },
    {
      "name": "vite:build-html",
      "start": 1746125696680,
      "end": 1746125696680,
      "order": "normal-normal"
    },
    {
      "name": "vite:dynamic-import-vars",
      "start": 1746125696680,
      "end": 1746125696680,
      "order": "normal-normal"
    },
    {
      "name": "vite:import-glob",
      "start": 1746125696680,
      "end": 1746125696680,
      "order": "normal-normal"
    },
    {
      "name": "vike:extractAssets:remove-javaScript",
      "start": 1746125696680,
      "end": 1746125696680,
      "order": "post"
    },
    {
      "name": "vike:extractExportNames",
      "start": 1746125696680,
      "end": 1746125696680,
      "order": "post"
    },
    {
      "name": "vike:envVars",
      "start": 1746125696680,
      "end": 1746125696680,
      "order": "post"
    },
    {
      "name": "vite:build-import-analysis",
      "start": 1746125696680,
      "end": 1746125696680,
      "order": "normal-normal"
    },
    {
      "name": "vite:reporter",
      "start": 1746125696680,
      "end": 1746125696680,
      "order": "normal"
    },
    {
      "name": "vite:define",
      "start": 1746125696680,
      "end": 1746125696680,
      "order": "normal-normal"
    },
    {
      "name": "vike:pluginModuleBanner",
      "result": "/*! src/pages/IndexPage/ui/About/About.module.css [vike:pluginModuleBanner] */\nexport const grid = \"z9Uac\";\nexport const description = \"YrmH6\";\nexport const image = \"_28Q3-\";\nexport default {\n\tgrid: grid,\n\tdescription: description,\n\timage: image\n};\n",
      "start": 1746125696680,
      "end": 1746125696680,
      "order": "post-post",
      "sourcemaps": {
        "version": 3,
        "sources": ["src/pages/IndexPage/ui/About/About.module.css"],
        "names": [],
        "mappings": ";AAAA,CAAC,CAAC,CAAC,CAAC,CAAC,CAAC,CAAC,CAAC,CAAC,CAAC,CAAC,CAAC,CAAC,CAAC,CAAC,CAAC,CAAC,CAAC,CAAC,CAAC,CAAC,CAAC,CAAC,CAAC,CAAC,CAAC,CAAC;AAC3B,CAAC,CAAC,CAAC,CAAC,CAAC,CAAC,CAAC,CAAC,CAAC,CAAC,CAAC,CAAC,CAAC,CAAC,CAAC,CAAC,CAAC,CAAC,CAAC,CAAC,CAAC,CAAC,CAAC,CAAC,CAAC,CAAC,CAAC,CAAC,CAAC,CAAC,CAAC,CAAC,CAAC,CAAC;AAClC,CAAC,CAAC,CAAC,CAAC,CAAC,CAAC,CAAC,CAAC,CAAC,CAAC,CAAC,CAAC,CAAC,CAAC,CAAC,CAAC,CAAC,CAAC,CAAC,CAAC,CAAC,CAAC,CAAC,CAAC,CAAC,CAAC,CAAC,CAAC,CAAC;AAC7B,CAAC,CAAC,CAAC,CAAC,CAAC,CAAC,CAAC,CAAC,CAAC,CAAC,CAAC,CAAC,CAAC,CAAC,CAAC;AACf,CAAC,CAAC,CAAC,CAAC,CAAC,CAAC,CAAC,CAAC,CAAC,CAAC,CAAC;AACX,CAAC,CAAC,CAAC,CAAC,CAAC,CAAC,CAAC,CAAC,CAAC,CAAC,CAAC,CAAC,CAAC,CAAC,CAAC,CAAC,CAAC,CAAC,CAAC,CAAC,CAAC,CAAC,CAAC,CAAC,CAAC;AACzB,CAAC,CAAC,CAAC,CAAC,CAAC,CAAC,CAAC,CAAC,CAAC,CAAC,CAAC,CAAC;AACZ,CAAC;"
      }
    }
  ]
}
